AUTHORS
MANIFEST.in
setup.py
bin/patin
patin/__init__.py
patin/bottle.py
patin/controlador.py
patin/patin_version.py
patin/programas.py
patin/syntax.py
patin/test.py
patin/utils.py
patin.egg-info/PKG-INFO
patin.egg-info/SOURCES.txt
patin.egg-info/dependency_links.txt
patin.egg-info/requires.txt
patin.egg-info/top_level.txt
patin/documentacion/.buildinfo
patin/documentacion/__init__.py
patin/documentacion/genindex.html
patin/documentacion/haciendo_juegos.html
patin/documentacion/haciendo_juegos_fisica.html
patin/documentacion/index.html
patin/documentacion/inicio.html
patin/documentacion/mis_programas.html
patin/documentacion/objects.inv
patin/documentacion/primeros_pasos.html
patin/documentacion/programas.html
patin/documentacion/search.html
patin/documentacion/searchindex.js
patin/documentacion/_images/aviso.png
patin/documentacion/_images/bomba.png
patin/documentacion/_images/nave.png
patin/documentacion/_images/patin.png
patin/documentacion/_sources/haciendo_juegos.txt
patin/documentacion/_sources/haciendo_juegos_fisica.txt
patin/documentacion/_sources/index.txt
patin/documentacion/_sources/inicio.txt
patin/documentacion/_sources/mis_programas.txt
patin/documentacion/_sources/primeros_pasos.txt
patin/documentacion/_sources/programas.txt
patin/documentacion/_static/ajax-loader.gif
patin/documentacion/_static/alert_info_32.png
patin/documentacion/_static/alert_warning_32.png
patin/documentacion/_static/basic.css
patin/documentacion/_static/bg-page.png
patin/documentacion/_static/bullet_orange.png
patin/documentacion/_static/comment-bright.png
patin/documentacion/_static/comment-close.png
patin/documentacion/_static/comment.png
patin/documentacion/_static/doctools.js
patin/documentacion/_static/down-pressed.png
patin/documentacion/_static/down.png
patin/documentacion/_static/extra.js
patin/documentacion/_static/file.png
patin/documentacion/_static/haiku.css
patin/documentacion/_static/jquery.js
patin/documentacion/_static/minus.png
patin/documentacion/_static/plus.png
patin/documentacion/_static/pygments.css
patin/documentacion/_static/searchtools.js
patin/documentacion/_static/translations.js
