Metadata-Version: 1.0
Name: patin
Version: 0.1.8
Summary: Simple develop kit for kids and programming teachers.
Home-page: http://www.patin.ep.io
Author: Hugo Ruscitti
Author-email: hugoruscitti@gmail.com
License: UNKNOWN
Platform: UNKNOWN
Classifier: Intended Audience :: Developers
Classifier: Intended Audience :: Education
Classifier: License :: OSI Approved :: GNU Library or Lesser General Public License (LGPL)
Classifier: Natural Language :: Spanish
Classifier: Operating System :: OS Independent
Classifier: Programming Language :: Python
Classifier: Topic :: Games/Entertainment
Classifier: Topic :: Education
Classifier: Topic :: Software Development :: Libraries
